aicodec/__init__.py
aicodec/py.typed
aicodec/application/__init__.py
aicodec/application/services.py
aicodec/assets/decoder_schema.json
aicodec/assets/prompts/base.j2
aicodec/assets/prompts/full.j2
aicodec/assets/prompts/minimal.j2
aicodec/domain/__init__.py
aicodec/domain/models.py
aicodec/domain/repositories.py
aicodec/infrastructure/__init__.py
aicodec/infrastructure/config.py
aicodec/infrastructure/map_generator.py
aicodec/infrastructure/utils.py
aicodec/infrastructure/cli/__init__.py
aicodec/infrastructure/cli/command_line_interface.py
aicodec/infrastructure/cli/commands/__init__.py
aicodec/infrastructure/cli/commands/aggregate.py
aicodec/infrastructure/cli/commands/apply.py
aicodec/infrastructure/cli/commands/buildmap.py
aicodec/infrastructure/cli/commands/init.py
aicodec/infrastructure/cli/commands/prepare.py
aicodec/infrastructure/cli/commands/prompt.py
aicodec/infrastructure/cli/commands/revert.py
aicodec/infrastructure/cli/commands/schema.py
aicodec/infrastructure/cli/commands/utils.py
aicodec/infrastructure/repositories/__init__.py
aicodec/infrastructure/repositories/file_system_repository.py
aicodec/infrastructure/web/__init__.py
aicodec/infrastructure/web/server.py
aicodec/infrastructure/web/ui/index.html
aicodec-2.9.0.dist-info/licenses/LICENSE
aicodec-2.9.0.dist-info/METADATA
aicodec-2.9.0.dist-info/WHEEL
aicodec-2.9.0.dist-info/entry_points.txt
aicodec-2.9.0.dist-info/top_level.txt
aicodec-2.9.0.dist-info/RECORD
