Metadata-Version: 2.4
Name: aicodec
Version: 2.9.0
Summary: A lightweight communication layer for developers to interact with LLMs.
Author: Steffen Krakau
License: MIT License
Project-URL: Homepage, https://github.com/Stevie1704/aicodec
Project-URL: Bug Tracker, https://github.com/Stevie1704/aicodec/issues
Classifier: Development Status :: 5 - Production/Stable
Classifier: Intended Audience :: Developers
Classifier: Topic :: Software Development :: Code Generators
Classifier: Topic :: Utilities
Classifier: License :: OSI Approved :: MIT License
Classifier: Programming Language :: Python :: 3
Classifier: Programming Language :: Python :: 3.10
Classifier: Programming Language :: Python :: 3.11
Classifier: Programming Language :: Python :: 3.12
Classifier: Programming Language :: Python :: 3.13
Classifier: Programming Language :: Python :: 3.14
Classifier: Programming Language :: Python :: 3.15
Requires-Python: >=3.10
License-File: LICENSE
Requires-Dist: jsonschema
Requires-Dist: pyperclip
Requires-Dist: pathspec
Requires-Dist: tiktoken
Requires-Dist: jinja2
Requires-Dist: rich
Provides-Extra: dev
Requires-Dist: pytest; extra == "dev"
Requires-Dist: pytest-mock; extra == "dev"
Requires-Dist: pytest-cov; extra == "dev"
Requires-Dist: pytest-html; extra == "dev"
Requires-Dist: mypy; extra == "dev"
Requires-Dist: ruff; extra == "dev"
Requires-Dist: bandit; extra == "dev"
Requires-Dist: pre-commit; extra == "dev"
Requires-Dist: codespell; extra == "dev"
Requires-Dist: mkdocs; extra == "dev"
Requires-Dist: mkdocs-material; extra == "dev"
Requires-Dist: pyinstaller; extra == "dev"
Dynamic: license-file
